ManejadorMySQL/MySQL.py
ManejadorMySQL/__init__.py
ManejadorMySQL-0.0.1.dist-info/METADATA
ManejadorMySQL-0.0.1.dist-info/WHEEL
ManejadorMySQL-0.0.1.dist-info/top_level.txt
ManejadorMySQL-0.0.1.dist-info/RECORD
