Metadata-Version: 2.1
Name: ManejadorMySQL
Version: 0.0.1
Summary: Manejador de funciones MySQL
Home-page: https://github.com/sebasmedina2003
Author: Sebastián Medina
Author-email: sebasmedina2003@gmail.com
License: MIT
Requires-Dist: mysql.connector
